pwm.v
module pwm(

input clk,
input reset,
input [7:0] duty_cycle,

output reg pwm_out

);

reg [7:0] counter;

always @(posedge clk or posedge reset)
begin

if(reset)
begin
counter<=0;
pwm_out<=0;
end

else
begin

counter<=counter+1;

if(counter<duty_cycle)
pwm_out<=1;

else
pwm_out<=0;

end

end

endmodule

smart_home_controller.v
module smart_home_controller(

input clk,
input reset,

input motion_sensor,
input light_sensor,
input temp_high,
input door_open,

input manual_override,
input security_mode,

input [1:0] scene_select,

input force_light,
input force_fan,
input force_ac,

output alarm,
output light_pwm,
output fan_pwm,

output reg ac,
output reg energy_save

);

reg [7:0] light_level;
reg [7:0] fan_speed;

always @(posedge clk or posedge reset)

begin

if(reset)

begin

light_level<=0;
fan_speed<=0;

ac<=0;

energy_save<=0;

end

else

begin

if(force_light)
light_level<=255;

else if(motion_sensor && !light_sensor)
light_level<=200;

else
light_level<=0;


if(force_fan)

fan_speed<=255;

else if(temp_high)

fan_speed<=180;

else

fan_speed<=0;


if(force_ac)

ac<=1;

else

ac<=temp_high;

end

end

assign alarm=(security_mode && door_open);

pwm light_unit(

.clk(clk),
.reset(reset),
.duty_cycle(light_level),
.pwm_out(light_pwm)

);

pwm fan_unit(

.clk(clk),
.reset(reset),
.duty_cycle(fan_speed),
.pwm_out(fan_pwm)

);

endmodule

sensor_generator.v
module sensor_generator(

input clk,
input reset,

output reg motion_sensor,
output reg light_sensor,
output reg temp_high,
output reg door_open

);

reg [7:0] counter;

always @(posedge clk or posedge reset)

begin

if(reset)

begin

counter<=0;

motion_sensor<=0;
light_sensor<=1;
temp_high<=0;
door_open<=0;

end

else

begin

counter<=counter+1;

case(counter)

10:
begin
motion_sensor<=1;
light_sensor<=0;
end

30:
temp_high<=1;

50:
door_open<=1;

70:
begin
motion_sensor<=0;
temp_high<=0;
door_open<=0;
end

endcase

end

end

endmodule

smart_home_tb.v
`timescale 1ns/1ps

module smart_home_tb;

reg clk=0;
reg reset;

wire motion_sensor;
wire light_sensor;
wire temp_high;
wire door_open;

wire alarm;
wire light_pwm;
wire fan_pwm;
wire ac;
wire energy_save;

always #5 clk=~clk;

sensor_generator SENSOR(

.clk(clk),
.reset(reset),

.motion_sensor(motion_sensor),
.light_sensor(light_sensor),
.temp_high(temp_high),
.door_open(door_open)

);

smart_home_controller DUT(

.clk(clk),
.reset(reset),

.motion_sensor(motion_sensor),
.light_sensor(light_sensor),
.temp_high(temp_high),
.door_open(door_open),

.manual_override(0),
.security_mode(1),

.scene_select(0),

.force_light(0),
.force_fan(0),
.force_ac(0),

.alarm(alarm),

.light_pwm(light_pwm),
.fan_pwm(fan_pwm),

.ac(ac),
.energy_save(energy_save)

);

initial
begin

$dumpfile("smart_home.vcd");
$dumpvars(0,smart_home_tb);

reset=1;

#20;

reset=0;

#1000;

$finish;

end

always @(posedge clk)

begin

$display(
"%0t,%0d,%0d,%0d,%0d,%0d",
$time,
light_pwm,
fan_pwm,
ac,
alarm,
energy_save
);

end

endmodule

smart_home.vcd
$date
	Mon Jun 22 12:11:01 2026
$end
$version
	Icarus Verilog
$end
$timescale
	1ps
$end
$scope module smart_home_tb $end
$var wire 1 ! temp_high $end
$var wire 1 " motion_sensor $end
$var wire 1 # light_sensor $end
$var wire 1 $ light_pwm $end
$var wire 1 % fan_pwm $end
$var wire 1 & energy_save $end
$var wire 1 ' door_open $end
$var wire 1 ( alarm $end
$var wire 1 ) ac $end
$var reg 1 * clk $end
$var reg 1 + reset $end
$scope module DUT $end
$var wire 1 ( alarm $end
$var wire 1 * clk $end
$var wire 1 , force_ac $end
$var wire 1 - force_fan $end
$var wire 1 . force_light $end
$var wire 1 / manual_override $end
$var wire 1 + reset $end
$var wire 2 0 scene_select [1:0] $end
$var wire 1 1 security_mode $end
$var wire 1 ! temp_high $end
$var wire 1 " motion_sensor $end
$var wire 1 # light_sensor $end
$var wire 1 $ light_pwm $end
$var wire 1 % fan_pwm $end
$var wire 1 ' door_open $end
$var reg 1 ) ac $end
$var reg 1 & energy_save $end
$var reg 8 2 fan_speed [7:0] $end
$var reg 8 3 light_level [7:0] $end
$scope module fan_unit $end
$var wire 1 * clk $end
$var wire 8 4 duty_cycle [7:0] $end
$var wire 1 + reset $end
$var reg 8 5 counter [7:0] $end
$var reg 1 % pwm_out $end
$upscope $end
$scope module light_unit $end
$var wire 1 * clk $end
$var wire 8 6 duty_cycle [7:0] $end
$var wire 1 + reset $end
$var reg 8 7 counter [7:0] $end
$var reg 1 $ pwm_out $end
$upscope $end
$upscope $end
$scope module SENSOR $end
$var wire 1 * clk $end
$var wire 1 + reset $end
$var reg 8 8 counter [7:0] $end
$var reg 1 ' door_open $end
$var reg 1 # light_sensor $end
$var reg 1 " motion_sensor $end
$var reg 1 ! temp_high $end
$upscope $end
$upscope $end
$enddefinitions $end
#0
$dumpvars
b0 8
b0 7
b0 6
b0 5
b0 4
b0 3
b0 2
11
b0 0
0/
0.
0-
0,
1+
0*
0)
0(
0'
0&
0%
0$
1#
0"
0!
$end
#5000
1*
#10000
0*
#15000
1*
#20000
0*
0+
#25000
b1 5
b1 7
b1 8
1*
#30000
0*
#35000
b10 8
b10 7
b10 5
1*
#40000
0*
#45000
b11 5
b11 7
b11 8
1*
#50000
0*
#55000
b100 8
b100 7
b100 5
1*
#60000
0*
#65000
b101 5
b101 7
b101 8
1*
#70000
0*
#75000
b110 8
b110 7
b110 5
1*
#80000
0*
#85000
b111 5
b111 7
b111 8
1*
#90000
0*
#95000
b1000 8
b1000 7
b1000 5
1*
#100000
0*
#105000
b1001 5
b1001 7
b1001 8
1*
#110000
0*
#115000
b1010 8
b1010 7
b1010 5
1*
#120000
0*
#125000
b1011 5
b1011 7
0#
1"
b1011 8
1*
#130000
0*
#135000
b1100 8
b1100 7
b1100 5
b11001000 3
b11001000 6
1*
#140000
0*
#145000
b1101 5
1$
b1101 7
b1101 8
1*
#150000
0*
#155000
b1110 8
b1110 7
b1110 5
1*
#160000
0*
#165000
b1111 5
b1111 7
b1111 8
1*
#170000
0*
#175000
b10000 8
b10000 7
b10000 5
1*
#180000
0*
#185000
b10001 5
b10001 7
b10001 8
1*
#190000
0*
#195000
b10010 8
b10010 7
b10010 5
1*
#200000
0*
#205000
b10011 5
b10011 7
b10011 8
1*
#210000
0*
#215000
b10100 8
b10100 7
b10100 5
1*
#220000
0*
#225000
b10101 5
b10101 7
b10101 8
1*
#230000
0*
#235000
b10110 8
b10110 7
b10110 5
1*
#240000
0*
#245000
b10111 5
b10111 7
b10111 8
1*
#250000
0*
#255000
b11000 8
b11000 7
b11000 5
1*
#260000
0*
#265000
b11001 5
b11001 7
b11001 8
1*
#270000
0*
#275000
b11010 8
b11010 7
b11010 5
1*
#280000
0*
#285000
b11011 5
b11011 7
b11011 8
1*
#290000
0*
#295000
b11100 8
b11100 7
b11100 5
1*
#300000
0*
#305000
b11101 5
b11101 7
b11101 8
1*
#310000
0*
#315000
b11110 8
b11110 7
b11110 5
1*
#320000
0*
#325000
b11111 5
b11111 7
1!
b11111 8
1*
#330000
0*
#335000
b100000 8
b100000 7
b100000 5
1)
b10110100 2
b10110100 4
1*
#340000
0*
#345000
1%
b100001 5
b100001 7
b100001 8
1*
#350000
0*
#355000
b100010 8
b100010 7
b100010 5
1*
#360000
0*
#365000
b100011 5
b100011 7
b100011 8
1*
#370000
0*
#375000
b100100 8
b100100 7
b100100 5
1*
#380000
0*
#385000
b100101 5
b100101 7
b100101 8
1*
#390000
0*
#395000
b100110 8
b100110 7
b100110 5
1*
#400000
0*
#405000
b100111 5
b100111 7
b100111 8
1*
#410000
0*
#415000
b101000 8
b101000 7
b101000 5
1*
#420000
0*
#425000
b101001 5
b101001 7
b101001 8
1*
#430000
0*
#435000
b101010 8
b101010 7
b101010 5
1*
#440000
0*
#445000
b101011 5
b101011 7
b101011 8
1*
#450000
0*
#455000
b101100 8
b101100 7
b101100 5
1*
#460000
0*
#465000
b101101 5
b101101 7
b101101 8
1*
#470000
0*
#475000
b101110 8
b101110 7
b101110 5
1*
#480000
0*
#485000
b101111 5
b101111 7
b101111 8
1*
#490000
0*
#495000
b110000 8
b110000 7
b110000 5
1*
#500000
0*
#505000
b110001 5
b110001 7
b110001 8
1*
#510000
0*
#515000
b110010 8
b110010 7
b110010 5
1*
#520000
0*
#525000
1(
b110011 5
b110011 7
1'
b110011 8
1*
#530000
0*
#535000
b110100 8
b110100 7
b110100 5
1*
#540000
0*
#545000
b110101 5
b110101 7
b110101 8
1*
#550000
0*
#555000
b110110 8
b110110 7
b110110 5
1*
#560000
0*
#565000
b110111 5
b110111 7
b110111 8
1*
#570000
0*
#575000
b111000 8
b111000 7
b111000 5
1*
#580000
0*
#585000
b111001 5
b111001 7
b111001 8
1*
#590000
0*
#595000
b111010 8
b111010 7
b111010 5
1*
#600000
0*
#605000
b111011 5
b111011 7
b111011 8
1*
#610000
0*
#615000
b111100 8
b111100 7
b111100 5
1*
#620000
0*
#625000
b111101 5
b111101 7
b111101 8
1*
#630000
0*
#635000
b111110 8
b111110 7
b111110 5
1*
#640000
0*
#645000
b111111 5
b111111 7
b111111 8
1*
#650000
0*
#655000
b1000000 8
b1000000 7
b1000000 5
1*
#660000
0*
#665000
b1000001 5
b1000001 7
b1000001 8
1*
#670000
0*
#675000
b1000010 8
b1000010 7
b1000010 5
1*
#680000
0*
#685000
b1000011 5
b1000011 7
b1000011 8
1*
#690000
0*
#695000
b1000100 8
b1000100 7
b1000100 5
1*
#700000
0*
#705000
b1000101 5
b1000101 7
b1000101 8
1*
#710000
0*
#715000
b1000110 8
b1000110 7
b1000110 5
1*
#720000
0*
#725000
0(
b1000111 5
b1000111 7
0'
0!
0"
b1000111 8
1*
#730000
0*
#735000
b1001000 8
b1001000 7
b1001000 5
0)
b0 2
b0 4
b0 3
b0 6
1*
#740000
0*
#745000
0%
b1001001 5
0$
b1001001 7
b1001001 8
1*
#750000
0*
#755000
b1001010 8
b1001010 7
b1001010 5
1*
#760000
0*
#765000
b1001011 5
b1001011 7
b1001011 8
1*
#770000
0*
#775000
b1001100 8
b1001100 7
b1001100 5
1*
#780000
0*
#785000
b1001101 5
b1001101 7
b1001101 8
1*
#790000
0*
#795000
b1001110 8
b1001110 7
b1001110 5
1*
#800000
0*
#805000
b1001111 5
b1001111 7
b1001111 8
1*
#810000
0*
#815000
b1010000 8
b1010000 7
b1010000 5
1*
#820000
0*
#825000
b1010001 5
b1010001 7
b1010001 8
1*
#830000
0*
#835000
b1010010 8
b1010010 7
b1010010 5
1*
#840000
0*
#845000
b1010011 5
b1010011 7
b1010011 8
1*
#850000
0*
#855000
b1010100 8
b1010100 7
b1010100 5
1*
#860000
0*
#865000
b1010101 5
b1010101 7
b1010101 8
1*
#870000
0*
#875000
b1010110 8
b1010110 7
b1010110 5
1*
#880000
0*
#885000
b1010111 5
b1010111 7
b1010111 8
1*
#890000
0*
#895000
b1011000 8
b1011000 7
b1011000 5
1*
#900000
0*
#905000
b1011001 5
b1011001 7
b1011001 8
1*
#910000
0*
#915000
b1011010 8
b1011010 7
b1011010 5
1*
#920000
0*
#925000
b1011011 5
b1011011 7
b1011011 8
1*
#930000
0*
#935000
b1011100 8
b1011100 7
b1011100 5
1*
#940000
0*
#945000
b1011101 5
b1011101 7
b1011101 8
1*
#950000
0*
#955000
b1011110 8
b1011110 7
b1011110 5
1*
#960000
0*
#965000
b1011111 5
b1011111 7
b1011111 8
1*
#970000
0*
#975000
b1100000 8
b1100000 7
b1100000 5
1*
#980000
0*
#985000
b1100001 5
b1100001 7
b1100001 8
1*
#990000
0*
#995000
b1100010 8
b1100010 7
b1100010 5
1*
#1000000
0*
#1005000
b1100011 5
b1100011 7
b1100011 8
1*
#1010000
0*
#1015000
b1100100 8
b1100100 7
b1100100 5
1*
